ptt_article_parser/__init__.py
ptt_article_parser/__main__.py
ptt_article_parser/dir.py
ptt_article_parser/helper.py
ptt_article_parser/rename.py
ptt_article_parser-0.6.0.dist-info/LICENSE
ptt_article_parser-0.6.0.dist-info/METADATA
ptt_article_parser-0.6.0.dist-info/WHEEL
ptt_article_parser-0.6.0.dist-info/entry_points.txt
ptt_article_parser-0.6.0.dist-info/top_level.txt
ptt_article_parser-0.6.0.dist-info/zip-safe
ptt_article_parser-0.6.0.dist-info/RECORD
