Metadata-Version: 2.1
Name: ptt-article-parser
Version: 0.6.0
Summary: A renaming tool for PTT articles
Home-page: https://github.com/eight04/ptt-article-parser
Author: eight
Author-email: eight04@gmail.com
License: MIT
Keywords: ptt,article,parser
Platform: UNKNOWN
Classifier: Development Status :: 4 - Beta
Classifier: Environment :: Console
Classifier: Environment :: Win32 (MS Windows)
Classifier: Intended Audience :: Developers
Classifier: Intended Audience :: End Users/Desktop
Classifier: License :: OSI Approved :: MIT License
Classifier: Natural Language :: Chinese (Traditional)
Classifier: Operating System :: Microsoft :: Windows :: Windows 7
Classifier: Programming Language :: Python :: 3.5
Classifier: Topic :: Terminals
Requires-Dist: docopt (~=0.6.2)
Requires-Dist: safeprint (~=0.2.0)
Requires-Dist: uao (~=0.2.0)
